hgt/__init__.py
hgt-0.0.0.dist-info/LICENSE
hgt-0.0.0.dist-info/METADATA
hgt-0.0.0.dist-info/WHEEL
hgt-0.0.0.dist-info/top_level.txt
hgt-0.0.0.dist-info/RECORD
