Metadata-Version: 2.1
Name: hgt
Version: 0.0.0
Summary: A work in progress package
Home-page: https://github.com/not-a-feature/
Author: Jules Kreuer / not_a_feature
License: gpl-3.0
Keywords: bioinformatics
Platform: unix
Platform: linux
Platform: osx
Platform: cygwin
Platform: win32
Classifier: Programming Language :: Python :: 3
Classifier: Programming Language :: Python :: 3.8
Classifier: Programming Language :: Python :: 3.9
Requires-Python: >=3.8
License-File: LICENSE
Provides-Extra: testing
Requires-Dist: pytest (>=6.0) ; extra == 'testing'
Requires-Dist: pytest-cov (>=2.0) ; extra == 'testing'
Requires-Dist: flake8 (>=3.9) ; extra == 'testing'
Requires-Dist: tox (>=3.20) ; extra == 'testing'
